{"gamehistory":["{\"gameID\":\"a471dc80-2331-4e24-aad8-86773f3d2e3b\",\"subject\":\"{\\\"subjectDescription\\\":\\\"An Introduction to Object Oriented Programming\\\",\\\"questionsList\\\":[],\\\"subjectID\\\":\\\"04a48783-385e-4da9-b694-8f95607339fe\\\",\\\"subjectName\\\":\\\"JAVA I\\\"}\",\"player\":\"{\\\"bestTime\\\":10.0,\\\"score\\\":100.0,\\\"name\\\":\\\"Austin Powers\\\",\\\"playerID\\\":\\\"af3978b9-70be-453c-93d9-cd35f0893775\\\"}\"}"],"player":"{\"bestTime\":10.0,\"score\":100.0,\"name\":\"Austin Powers\",\"playerID\":\"af3978b9-70be-453c-93d9-cd35f0893775\"}"}